isocirc/__init__.py
isocirc/bam_classify.py
isocirc/basic_stats.py
isocirc/cons_align.py
isocirc/cons_call.py
isocirc/error_corr.py
isocirc/hcBSJ_fullIso.py
isocirc/isocirc_comp.py
isocirc/isocirc_find_IR.py
isocirc/isocirc_stats.py
isocirc/parse_bam.py
isocirc/parse_gff.py
isocirc/tandem_repeat.py
isocirc/uniq_isoform.py
isocirc/utils.py
isocirc/plot/__init__.py
isocirc/plot/circ_plot.py
isocirc/plot/disToKnownPlot.py
isocirc/plot/histogramPlot.py
isocirc/plot/line_plot.py
isocirc/plot/percAreaPlot.py
isocirc/plot/pieChart.py
isocirc/plot/plot_config.py
isocirc/plot/stackedBarPlot.py
isocirc/plot/vennDiagram.py
isocirc-1.0.7.data/data/bin/bedToGenePred
isocirc-1.0.7.data/data/bin/fxtools
isocirc-1.0.7.data/data/bin/genePredToBed
isocirc-1.0.7.data/data/bin/genePredToGtf
isocirc-1.0.7.data/data/bin/gtfToGenePred
isocirc-1.0.7.data/data/bin/lordec-correct
isocirc-1.0.7.data/data/bin/trf409.legacylinux64
isocirc-1.0.7.data/scripts/bed2exonGtf
isocirc-1.0.7.data/scripts/bed2gtf
isocirc-1.0.7.data/scripts/gtf2bed
isocirc-1.0.7.data/scripts/gtf2gene
isocirc-1.0.7.data/scripts/isocirc
isocirc-1.0.7.data/scripts/isocirc2bed12
isocirc-1.0.7.data/scripts/isocircPlot
isocirc-1.0.7.data/scripts/itst_gtf_bed
isocirc-1.0.7.data/scripts/itst_gtf_gtf
isocirc-1.0.7.dist-info/METADATA
isocirc-1.0.7.dist-info/WHEEL
isocirc-1.0.7.dist-info/top_level.txt
isocirc-1.0.7.dist-info/RECORD
