Metadata-Version: 2.1
Name: isocirc
Version: 1.0.7
Summary: isoCirc: computational pipeline to identify high-confidence BSJs and full-length circRNA isoforms from isoCirc long-read data
Home-page: https://github.com/Xinglab/isoCirc
Author: Yan Gao
Author-email: gaoy1@chop.edu
License: GLP
Requires-Dist: biopython (>=1.80)
Requires-Dist: gffutils
Requires-Dist: pyinterval
Requires-Dist: mappy (>=2.11)
Requires-Dist: matplotlib
Requires-Dist: numpy
Requires-Dist: pandas
Requires-Dist: pyfaidx
Requires-Dist: pysam
